tw_dayoff/__init__.py
tw_dayoff/__main__.py
tw_dayoff/main.py
tw_dayoff-0.1.2.dist-info/LICENSE
tw_dayoff-0.1.2.dist-info/METADATA
tw_dayoff-0.1.2.dist-info/WHEEL
tw_dayoff-0.1.2.dist-info/top_level.txt
tw_dayoff-0.1.2.dist-info/RECORD
