Metadata-Version: 2.1
Name: tw-dayoff
Version: 0.1.2
Summary: A simple Python package to get Taiwan's dayoff information.
Author-email: Neko No Akuma <nekotw@dybts.us.kg>
License:                     GNU GENERAL PUBLIC LICENSE
Project-URL: Homepage, https://dybts.us.kg
Project-URL: Documentation, https://dybts.us.kg/
Project-URL: Repository, https://github.com/Neko-No-Akuma-TW/tw-dayoff
Keywords: taiwan,tw,dayoff,holiday
Classifier: Development Status :: 3 - Alpha
Classifier: Intended Audience :: Developers
Classifier: License :: OSI Approved :: MIT License
Classifier: Programming Language :: Python :: 3
Classifier: Programming Language :: Python :: 3.6
Classifier: Programming Language :: Python :: 3.7
Classifier: Programming Language :: Python :: 3.8
Classifier: Programming Language :: Python :: 3.9
Classifier: Programming Language :: Python :: 3.10
Classifier: Programming Language :: Python :: 3 :: Only
Classifier: Topic :: Software Development :: Libraries
Classifier: Topic :: Software Development :: Libraries :: Python Modules
Classifier: Topic :: Utilities
Requires-Python: >=3.6
License-File: LICENSE
Requires-Dist: requests
